nurin/__about__.py
nurin/__init__.py
nurin/__main__.py
nurin/cli.py
nurin/helpers.py
nurin/models.py
nurin/network.py
nurin/run.py
nurin-0.0.1.dist-info/METADATA
nurin-0.0.1.dist-info/WHEEL
nurin-0.0.1.dist-info/entry_points.txt
nurin-0.0.1.dist-info/licenses/LICENSE.txt
nurin-0.0.1.dist-info/RECORD
