Metadata-Version: 2.1
Name: nurin
Version: 0.0.1
Summary: Taasko se netti on nurin
Project-URL: Documentation, https://github.com/akx/nurin#readme
Project-URL: Issues, https://github.com/akx/nurin/issues
Project-URL: Source, https://github.com/akx/nurin
Author-email: Aarni Koskela <akx@iki.fi>
License-Expression: MIT
License-File: LICENSE.txt
Classifier: Development Status :: 4 - Beta
Classifier: Programming Language :: Python
Classifier: Programming Language :: Python :: 3.7
Classifier: Programming Language :: Python :: 3.8
Classifier: Programming Language :: Python :: 3.9
Classifier: Programming Language :: Python :: 3.10
Classifier: Programming Language :: Python :: 3.11
Classifier: Programming Language :: Python :: Implementation :: CPython
Classifier: Programming Language :: Python :: Implementation :: PyPy
Requires-Python: >=3.7
Requires-Dist: click
